<?xml version="1.0" encoding="UTF-8" standalone="no" ?>
<root>
    <TecCategoryType>TC_Technologies</TecCategoryType>
    <TimeToResearch>45</TimeToResearch>
    <ResourceCosts>
        <Silver>0</Silver>
        <Knowledge>2</Knowledge>
        <Stone>200</Stone>
    </ResourceCosts>
    <AutomaticResearch>true</AutomaticResearch>
    <UseForStatisticsFlag>true</UseForStatisticsFlag>
    <Conditions>
        <RequiredTecConditions>1</RequiredTecConditions>
        <TecCondition>
            <TecType>T_TownGuard</TecType>
            <TecCategoryType/>
        </TecCondition>

        <RequiredEntityConditions>1</RequiredEntityConditions>
        <EntityCondition>
            <EntityType>PB_VillageCenter1</EntityType>
            <Amount>1</Amount>
        </EntityCondition>
        <EntityCondition>
            <EntityType>PB_VillageCenter2</EntityType>
            <Amount>1</Amount>
        </EntityCondition>
        <EntityCondition>
            <EntityType>PB_VillageCenter3</EntityType>
            <Amount>1</Amount>
        </EntityCondition>
    </Conditions>
    </Conditions>
</root>
