<?xml version="1.0" encoding="UTF-8" standalone="no" ?>
<root>
    <!-- This is drakes passive ability technology! -->
    <TecCategoryType>TC_Technologies</TecCategoryType>
    <TimeToResearch>90</TimeToResearch>
    <ResourceCosts>
		<Silver>0</Silver>
		<Knowledge>8</Knowledge>
        <Gold>0</Gold>
        <Clay>0</Clay>
        <Wood>0</Wood>
        <Stone>0</Stone>
        <Iron>500</Iron>
        <Sulfur>0</Sulfur>
    </ResourceCosts>

    <DamageModifier>
		<Value>2</Value>
		<Operation>+</Operation>
	</DamageModifier>

    <AutomaticResearch>true</AutomaticResearch>
    <UseForStatisticsFlag>false</UseForStatisticsFlag>
    <Conditions>
    </Conditions>
</root>
