<?xml version="1.0" encoding="utf-8" standalone="no" ?>
<root>
    <Display classname="ED::CDisplayEntityProps">
        <Class>GD::CDisplaySettler</Class>
        <Model>CU_BanditLeaderSword1</Model>
        <DrawPlayerColor>True</DrawPlayerColor>
        <Anim>CU_BanditLeaderSword1_Walk</Anim>
		<Anim>CU_BanditLeaderSword1_Run1</Anim>
		<Anim>CU_BanditLeaderSword1_Idle1</Anim>
		<Anim>CU_BanditLeaderSword1_Idle2</Anim>
		<Anim>CU_BanditLeaderSword1_Idle3</Anim>
		<Anim>CU_BanditLeaderSword1_Idle4</Anim>
		<Anim>CU_BanditLeaderSword1_Idle5</Anim>
		<Anim>CU_BanditLeaderSword1_Idle6</Anim>
		<Anim>CU_BanditLeaderSword1_IdleAttack1</Anim>
		<Anim>CU_BanditLeaderSword1_Attack1</Anim>
		<Anim>CU_BanditLeaderSword1_Attack2</Anim>
		<Anim>CU_BanditLeaderSword1_Finish</Anim>
		<Anim>CU_BanditLeaderSword1_Hit</Anim>		
		<Anim>CU_BanditLeaderSword1_Dying1</Anim>
    </Display>
    <Logic classname="GGL::CGLSettlerProps">
        <Class>GGL::CSettler</Class>
        <AccessCategory>AccessCategorySettler</AccessCategory>
        <MaxHealth>225</MaxHealth>
        <NeedsPlayer>true</NeedsPlayer>
        <ForceNoPlayer>false</ForceNoPlayer>
        <Hat/>
        <Category>Military</Category>
        <Category>Leader</Category>
        <Category>Melee</Category>
        <Category>Sword</Category>
        <AdjustWalkAnimSpeed>true</AdjustWalkAnimSpeed>
        <ArmorClass>ArmorClassLeather</ArmorClass>
        <IdleTaskList>TL_MILITARY_IDLE</IdleTaskList>
        <Exploration>20</Exploration>
        <ArmorAmount>3</ArmorAmount>
        <ExperiencePoints>20</ExperiencePoints>
        <AttractionSlots>0</AttractionSlots>
        <DodgeChance>10</DodgeChance>
        <Cost>
            <Gold>0</Gold>
        </Cost>
        <Upgrade>
            <Category>BanditLeaderSword1</Category>
        </Upgrade>


        <ModifyArmor>
            <Technology>T_LeatherMailArmor</Technology>
        </ModifyArmor>
        <ModifyArmor>
            <Technology>T_ChainMailArmor</Technology>
        </ModifyArmor>
        <ModifyArmor>
            <Technology>T_PlateMailArmor</Technology>
        </ModifyArmor>

        <ModifyDamage>
            <Technology>T_MasterOfSmithery</Technology>
        </ModifyDamage>
        <ModifyDamage>
            <Technology>T_IronCasting</Technology>
        </ModifyDamage>

        <ModifySpeed>
            <Technology>T_BetterTrainingBarracks</Technology>
        </ModifySpeed>
    </Logic>
    <Behavior>
        <Logic classname="GGL::CGLAnimationBehaviorExProps">
            <Class>GGL::CGLBehaviorAnimationEx</Class>
            <AnimSet>SET_BANDITLEADERSWORD1</AnimSet>
        </Logic>
        <Display classname="ED::CBehaviorProps">
            <Class>ED::CDisplayBehaviorAnimation</Class>
        </Display>
    </Behavior>
    <Behavior>
        <Logic classname="EGL::CMovementBehaviorProps">
            <Class>GGL::CSettlerMovement</Class>
            <Speed>360</Speed>
            <RotationSpeed>30</RotationSpeed>
            <MoveTaskList>TL_LEADER_WALK</MoveTaskList>
        </Logic>
        <Display classname="ED::CBehaviorProps">
            <Class>ED::CDisplayBehaviorMovement</Class>
        </Display>
    </Behavior>
    <Behavior>
        <Logic classname="EGL::CGLEBehaviorProps">
            <Class>GGL::CBehaviorWalkCommand</Class>
        </Logic>
    </Behavior>
    <Behavior>
        <Logic classname="GGL::CLeaderBehaviorProps">
            <Class>GGL::CLeaderBehavior</Class>
            <SoldierType>CU_BanditSoldierSword3</SoldierType>
            <BarrackUpgradeCategory>Barracks</BarrackUpgradeCategory>
            <HomeRadius>3000</HomeRadius>

            <BattleTaskList>TL_BATTLE</BattleTaskList>

            <NormalAttackAnim1>CU_BanditLeaderSword1_Attack1</NormalAttackAnim1>
	        <NormalAttackAnim2>CU_BanditLeaderSword1_Attack2</NormalAttackAnim2>
	        <CounterAttackAnim>CU_BanditLeaderSword1_Finish</CounterAttackAnim>
	        <FinishingMoveAnim>CU_BanditLeaderSword1_Attack1</FinishingMoveAnim>
	        <MissAttackAnim>CU_BanditLeaderSword1_Attack1</MissAttackAnim>
	        <BattleIdleAnim>CU_BanditLeaderSword1_Idle1</BattleIdleAnim>
	        <BattleWalkAnim>CU_BanditLeaderSword1_Walk</BattleWalkAnim>
            <HitAnim>CU_BanditLeaderSword1_Hit</HitAnim>

            <DamageClass>DC_Slash</DamageClass>
            <DamageAmount>7</DamageAmount>
            <MaxRandomDamageBonus>3</MaxRandomDamageBonus>

            <MaxRange>300</MaxRange>
            <MinRange>0</MinRange>
            <AutoAttackRange>2000</AutoAttackRange>

            <BattleWaitUntil>2000</BattleWaitUntil>

            <HealingPoints>5</HealingPoints>
            <HealingSeconds>3</HealingSeconds>

        </Logic>
    </Behavior>

    <Behavior>
        <Logic classname="GGL::CLimitedAttachmentBehaviorProperties">
            <Class>GGL::CLimitedAttachmentBehavior</Class>
            <Attachment>
                <Type>ATTACHMENT_LEADER_SOLDIER</Type>
                <Limit>6</Limit>
            </Attachment>
        </Logic>
    </Behavior>

    <Behavior>
        <Logic classname="GGL::CGLBehaviorPropsDying">
            <Class>GGL::CGLBehaviorDying</Class>
            <DyingTaskList>TL_DIE</DyingTaskList>
        </Logic>
    </Behavior>

    <Behavior>
        <Logic classname="EGL::CGLEBehaviorProps">
            <Class>GGL::CLeaderEvadeBehavior</Class>
        </Logic>
    </Behavior>

    <Behavior>
        <Logic classname="GGL::CEvadeExecutionBehaviorProps">
            <Class>GGL::CEvadeExecutionBehavior</Class>
            <BasePriority>400</BasePriority>
        </Logic>
    </Behavior>

    <Behavior>
        <Logic classname="GGL::CReplaceableEntityBehaviorProperties">
            <Class>GGL::CReplaceableEntityBehavior</Class>
            <EntityType>XD_DroppedSwordShield</EntityType>
        </Logic>
    </Behavior>
</root>
